aylien_message_puller/__init__.py
aylien_message_puller/example.py
aylien_message_puller-0.0.1.dist-info/LICENSE.txt
aylien_message_puller-0.0.1.dist-info/METADATA
aylien_message_puller-0.0.1.dist-info/WHEEL
aylien_message_puller-0.0.1.dist-info/top_level.txt
aylien_message_puller-0.0.1.dist-info/RECORD
