Metadata-Version: 2.1
Name: aylien-message-puller
Version: 0.0.1
Summary: Tool for pulling messages from pubsub subscriptions
Home-page: UNKNOWN
Author: AYLIEN Engineering
Author-email: eng-team@aylien.com
License: UNKNOWN
Platform: UNKNOWN
Classifier: Programming Language :: Python :: 3
Classifier: License :: OSI Approved :: MIT License
Classifier: Operating System :: OS Independent
Requires-Dist: google-api-core (==1.33.2)
Requires-Dist: google-cloud-pubsub (==1.1.0)
Requires-Dist: google-cloud-core (==1.1.0)
Requires-Dist: lz4 (==4.0.2)
